delphi/__init__.py
delphi/__main__.py
delphi/config.py
delphi/pipeline.py
delphi/utils.py
delphi/clients/__init__.py
delphi/clients/client.py
delphi/clients/offline.py
delphi/clients/openrouter.py
delphi/clients/types.py
delphi/explainers/__init__.py
delphi/explainers/contrastive_explainer.py
delphi/explainers/explainer.py
delphi/explainers/no_op_explainer.py
delphi/explainers/single_token_explainer.py
delphi/explainers/default/default.py
delphi/explainers/default/prompt_builder.py
delphi/explainers/default/prompts.py
delphi/latents/__init__.py
delphi/latents/cache.py
delphi/latents/collect_activations.py
delphi/latents/constructors.py
delphi/latents/latents.py
delphi/latents/loader.py
delphi/latents/neighbours.py
delphi/latents/samplers.py
delphi/log/result_analysis.py
delphi/scorers/__init__.py
delphi/scorers/scorer.py
delphi/scorers/classifier/classifier.py
delphi/scorers/classifier/detection.py
delphi/scorers/classifier/fuzz.py
delphi/scorers/classifier/intruder.py
delphi/scorers/classifier/sample.py
delphi/scorers/classifier/prompts/detection_prompt.py
delphi/scorers/classifier/prompts/fuzz_prompt.py
delphi/scorers/classifier/prompts/intruder_prompt.py
delphi/scorers/embedding/embedding.py
delphi/scorers/embedding/example_embedding.py
delphi/scorers/simulator/simulation/__init__.py
delphi/scorers/simulator/simulation/data_models.py
delphi/scorers/simulator/simulation/few_shot_examples.py
delphi/scorers/simulator/simulation/llm_interface.py
delphi/scorers/simulator/simulation/oai_simulator.py
delphi/scorers/simulator/simulation/scoring.py
delphi/scorers/simulator/simulation/simulator.py
delphi/scorers/simulator/simulation/types.py
delphi/scorers/surprisal/prompts.py
delphi/scorers/surprisal/surprisal.py
delphi/sparse_coders/__init__.py
delphi/sparse_coders/load_sparsify.py
delphi/sparse_coders/sparse_model.py
delphi/sparse_coders/custom/gemmascope.py
eai_delphi-0.1.1.dist-info/licenses/LICENSE
eai_delphi-0.1.1.dist-info/METADATA
eai_delphi-0.1.1.dist-info/WHEEL
eai_delphi-0.1.1.dist-info/top_level.txt
eai_delphi-0.1.1.dist-info/RECORD
