Metadata-Version: 2.4
Name: eai-delphi
Version: 0.1.1
Summary: Automated Interpretability
Keywords: interpretability,explainable-ai
Requires-Python: >=3.10
License-File: LICENSE
Requires-Dist: torch
Requires-Dist: datasets
Requires-Dist: transformers
Requires-Dist: orjson
Requires-Dist: eai-sparsify
Requires-Dist: safetensors
Requires-Dist: simple_parsing
Requires-Dist: jaxtyping
Requires-Dist: fire
Requires-Dist: blobfile
Requires-Dist: bitsandbytes
Requires-Dist: flask
Requires-Dist: vllm
Requires-Dist: aiofiles
Requires-Dist: sentence_transformers
Requires-Dist: anyio>=4.8.0
Requires-Dist: faiss-cpu
Requires-Dist: asyncer>=0.0.8
Requires-Dist: beartype
Provides-Extra: dev
Requires-Dist: pytest; extra == "dev"
Requires-Dist: pyright==1.1.378; extra == "dev"
Requires-Dist: pytest-beartype; extra == "dev"
Requires-Dist: pytest-asyncio; extra == "dev"
Requires-Dist: setuptools; extra == "dev"
Requires-Dist: pre-commit; extra == "dev"
Provides-Extra: visualize
Requires-Dist: kaleido==0.2.1; extra == "visualize"
Requires-Dist: plotly>=5.0.0rc2; extra == "visualize"
Requires-Dist: pandas; extra == "visualize"
Requires-Dist: ipywidgets; extra == "visualize"
Dynamic: license-file
